{
    "key": "group_64fb64520ebc8",
    "title": "Site Settings",
    "fields": [
        {
            "key": "field_64fb6452544d7",
            "label": "Color Palette",
            "name": "",
            "aria-label": "",
            "type": "tab",
            "instructions": "",
            "required": 0,
            "conditional_logic": 0,
            "wrapper": {
                "width": "",
                "class": "",
                "id": ""
            },
            "placement": "left",
            "endpoint": 0,
            "selected": 0
        },
        {
            "key": "field_64fb65fd544d8",
            "label": "Color Palette",
            "name": "color_palette",
            "aria-label": "",
            "type": "clone",
            "instructions": "",
            "required": 0,
            "conditional_logic": 0,
            "wrapper": {
                "width": "",
                "class": "",
                "id": ""
            },
            "clone": [
                "group_64fbe0a73c890"
            ],
            "display": "seamless",
            "layout": "block",
            "prefix_label": 0,
            "prefix_name": 0,
            "acfe_seamless_style": 0,
            "acfe_clone_modal": 0,
            "acfe_clone_modal_close": 0,
            "acfe_clone_modal_button": "",
            "acfe_clone_modal_size": "large"
        },
        {
            "key": "field_64fc232b4d5ad",
            "label": "Header",
            "name": "",
            "aria-label": "",
            "type": "tab",
            "instructions": "",
            "required": 0,
            "conditional_logic": 0,
            "wrapper": {
                "width": "",
                "class": "",
                "id": ""
            },
            "placement": "left",
            "endpoint": 0,
            "selected": 0
        },
        {
            "key": "field_64fc23364d5ae",
            "label": "Top Navigation",
            "name": "top_navigation",
            "aria-label": "",
            "type": "clone",
            "instructions": "",
            "required": 0,
            "conditional_logic": 0,
            "wrapper": {
                "width": "",
                "class": "",
                "id": ""
            },
            "clone": [
                "group_64fc2193aca21"
            ],
            "display": "seamless",
            "layout": "block",
            "prefix_label": 0,
            "prefix_name": 0,
            "acfe_seamless_style": 0,
            "acfe_clone_modal": 0,
            "acfe_clone_modal_close": 0,
            "acfe_clone_modal_button": "",
            "acfe_clone_modal_size": "large"
        },
        {
            "key": "field_64fc2ba8b6ca6",
            "label": "Header Logo",
            "name": "header_logo",
            "aria-label": "",
            "type": "clone",
            "instructions": "",
            "required": 0,
            "conditional_logic": 0,
            "wrapper": {
                "width": "",
                "class": "",
                "id": ""
            },
            "clone": [
                "group_64fc2a6351140"
            ],
            "display": "seamless",
            "layout": "block",
            "prefix_label": 0,
            "prefix_name": 0,
            "acfe_seamless_style": 0,
            "acfe_clone_modal": 0,
            "acfe_clone_modal_close": 0,
            "acfe_clone_modal_button": "",
            "acfe_clone_modal_size": "large"
        },
        {
            "key": "field_6765ce49438ab",
            "label": "Show Search",
            "name": "show_search",
            "aria-label": "",
            "type": "true_false",
            "instructions": "",
            "required": 0,
            "conditional_logic": 0,
            "wrapper": {
                "width": "",
                "class": "",
                "id": ""
            },
            "message": "",
            "default_value": 1,
            "ui_on_text": "",
            "ui_off_text": "",
            "ui": 1
        },
        {
            "key": "field_64fc551698932",
            "label": "Main Menu",
            "name": "",
            "aria-label": "",
            "type": "tab",
            "instructions": "",
            "required": 0,
            "conditional_logic": 0,
            "wrapper": {
                "width": "",
                "class": "",
                "id": ""
            },
            "placement": "left",
            "endpoint": 0,
            "selected": 0
        },
        {
            "key": "field_64fc552298933",
            "label": "Main Menu",
            "name": "main_menu",
            "aria-label": "",
            "type": "clone",
            "instructions": "",
            "required": 0,
            "conditional_logic": 0,
            "wrapper": {
                "width": "",
                "class": "",
                "id": ""
            },
            "clone": [
                "group_66a1a08450d34"
            ],
            "display": "seamless",
            "layout": "block",
            "prefix_label": 0,
            "prefix_name": 0,
            "acfe_seamless_style": 0,
            "acfe_clone_modal": 0,
            "acfe_clone_modal_close": 0,
            "acfe_clone_modal_button": "",
            "acfe_clone_modal_size": "large"
        },
        {
            "key": "field_653f01fe03cc9",
            "label": "Subscribe",
            "name": "",
            "aria-label": "",
            "type": "tab",
            "instructions": "",
            "required": 0,
            "conditional_logic": 0,
            "wrapper": {
                "width": "",
                "class": "",
                "id": ""
            },
            "placement": "top",
            "endpoint": 0,
            "selected": 0
        },
        {
            "key": "field_653f021603cca",
            "label": "Subscribe",
            "name": "subscribe",
            "aria-label": "",
            "type": "clone",
            "instructions": "",
            "required": 0,
            "conditional_logic": 0,
            "wrapper": {
                "width": "",
                "class": "",
                "id": ""
            },
            "clone": [
                "group_653f01d411101"
            ],
            "display": "seamless",
            "layout": "block",
            "prefix_label": 0,
            "prefix_name": 0,
            "acfe_seamless_style": 0,
            "acfe_clone_modal": 0,
            "acfe_clone_modal_close": 0,
            "acfe_clone_modal_button": "",
            "acfe_clone_modal_size": "large"
        },
        {
            "key": "field_64ff2376a6fda",
            "label": "Footer",
            "name": "",
            "aria-label": "",
            "type": "tab",
            "instructions": "",
            "required": 0,
            "conditional_logic": 0,
            "wrapper": {
                "width": "",
                "class": "",
                "id": ""
            },
            "placement": "top",
            "endpoint": 0,
            "selected": 0
        },
        {
            "key": "field_64ff2384a6fdb",
            "label": "Site Footer",
            "name": "site_footer",
            "aria-label": "",
            "type": "clone",
            "instructions": "",
            "required": 0,
            "conditional_logic": 0,
            "wrapper": {
                "width": "",
                "class": "",
                "id": ""
            },
            "clone": [
                "group_64ff201dba260"
            ],
            "display": "seamless",
            "layout": "block",
            "prefix_label": 0,
            "prefix_name": 0,
            "acfe_seamless_style": 0,
            "acfe_clone_modal": 0,
            "acfe_clone_modal_close": 0,
            "acfe_clone_modal_button": "",
            "acfe_clone_modal_size": "large"
        }
    ],
    "location": [
        [
            {
                "param": "options_page",
                "operator": "==",
                "value": "theme-settings"
            }
        ]
    ],
    "menu_order": 0,
    "position": "normal",
    "style": "default",
    "label_placement": "left",
    "instruction_placement": "label",
    "hide_on_screen": "",
    "active": true,
    "description": "",
    "show_in_rest": 0,
    "acfe_display_title": "",
    "acfe_autosync": [
        "json"
    ],
    "acfe_form": 0,
    "acfe_meta": "",
    "acfe_note": "",
    "modified": 1734725250,
    "acfe_categories": {
        "options": "Options",
        "site-settings": "Site Settings"
    }
}
